kishuboard/__init__.py
kishuboard/_version.py
kishuboard/server.py
kishuboard/build/asset-manifest.json
kishuboard/build/index.html
kishuboard/build/logo.png
kishuboard/build/robots.txt
kishuboard/build/static/css/main.e176ae11.css
kishuboard/build/static/css/main.e176ae11.css.map
kishuboard/build/static/js/787.ac117515.chunk.js
kishuboard/build/static/js/787.ac117515.chunk.js.map
kishuboard/build/static/js/main.3d8dc59c.js
kishuboard/build/static/js/main.3d8dc59c.js.LICENSE.txt
kishuboard/build/static/js/main.3d8dc59c.js.map
kishuboard-0.1.2.dist-info/METADATA
kishuboard-0.1.2.dist-info/WHEEL
kishuboard-0.1.2.dist-info/entry_points.txt
kishuboard-0.1.2.dist-info/licenses/LICENSE
kishuboard-0.1.2.dist-info/RECORD
