Metadata-Version: 2.4
Name: kishuboard
Version: 0.1.2
Dynamic: Author
Dynamic: Author-email
Dynamic: Summary
Dynamic: Keywords
Dynamic: Project-URL
License: BSD 3-Clause License
License-File: LICENSE
Classifier: Framework :: Jupyter
Classifier: Framework :: Jupyter :: JupyterLab
Classifier: Framework :: Jupyter :: JupyterLab :: 4
Classifier: Programming Language :: Python
Classifier: Programming Language :: Python :: 3
Classifier: Programming Language :: Python :: 3.8
Classifier: Programming Language :: Python :: 3.9
Classifier: Programming Language :: Python :: 3.10
Classifier: Programming Language :: Python :: 3.11
Requires-Python: >=3.8
Requires-Dist: flask
Requires-Dist: flask-cors
Requires-Dist: kishu
